{"cameraMode":{"drawMode":0,"name":"Shaded","section":"Shading Mode"},"sceneLighting":true,"audioPlay":false,"sceneViewState":{"showFog":true,"showMaterialUpdate":false,"showSkybox":true,"showFlares":true,"showImageEffects":true,"showParticleSystems":true},"in2DMode":false,"pivot":{"x":7.631463050842285,"y":-9.472517967224121,"z":-7.7642316818237309},"rotation":{"x":-0.15339748561382295,"y":-0.8400996327400208,"z":0.30648308992385867,"w":-0.420503705739975},"size":24.02454948425293,"orthographic":false}